odoo/addons/stock_picking_return_refund_option/README.rst
odoo/addons/stock_picking_return_refund_option/__init__.py
odoo/addons/stock_picking_return_refund_option/__manifest__.py
odoo/addons/stock_picking_return_refund_option/hooks.py
odoo/addons/stock_picking_return_refund_option/i18n/de.po
odoo/addons/stock_picking_return_refund_option/i18n/es.po
odoo/addons/stock_picking_return_refund_option/i18n/hr.po
odoo/addons/stock_picking_return_refund_option/i18n/pt.po
odoo/addons/stock_picking_return_refund_option/i18n/pt_BR.po
odoo/addons/stock_picking_return_refund_option/i18n/sl.po
odoo/addons/stock_picking_return_refund_option/i18n/stock_picking_return_refund_option.pot
odoo/addons/stock_picking_return_refund_option/models/__init__.py
odoo/addons/stock_picking_return_refund_option/models/stock_picking.py
odoo/addons/stock_picking_return_refund_option/readme/CONTRIBUTORS.rst
odoo/addons/stock_picking_return_refund_option/readme/DESCRIPTION.rst
odoo/addons/stock_picking_return_refund_option/readme/INSTALL.rst
odoo/addons/stock_picking_return_refund_option/readme/USAGE.rst
odoo/addons/stock_picking_return_refund_option/static/description/icon.png
odoo/addons/stock_picking_return_refund_option/static/description/index.html
odoo/addons/stock_picking_return_refund_option/tests/__init__.py
odoo/addons/stock_picking_return_refund_option/tests/test_stock_picking_return_refund_options.py
odoo/addons/stock_picking_return_refund_option/views/stock_picking_view.xml
odoo12_addon_stock_picking_return_refund_option-12.0.1.0.0.99.dev12.dist-info/METADATA
odoo12_addon_stock_picking_return_refund_option-12.0.1.0.0.99.dev12.dist-info/WHEEL
odoo12_addon_stock_picking_return_refund_option-12.0.1.0.0.99.dev12.dist-info/top_level.txt
odoo12_addon_stock_picking_return_refund_option-12.0.1.0.0.99.dev12.dist-info/RECORD
